README.md
setup.py
pulumi_stripe/__init__.py
pulumi_stripe/_inputs.py
pulumi_stripe/_utilities.py
pulumi_stripe/card.py
pulumi_stripe/coupon.py
pulumi_stripe/customer.py
pulumi_stripe/file.py
pulumi_stripe/outputs.py
pulumi_stripe/portal_configuration.py
pulumi_stripe/price.py
pulumi_stripe/product.py
pulumi_stripe/promotion_code.py
pulumi_stripe/provider.py
pulumi_stripe/pulumi-plugin.json
pulumi_stripe/py.typed
pulumi_stripe/shipping_rate.py
pulumi_stripe/tax_rate.py
pulumi_stripe/webhook_endpoint.py
pulumi_stripe.egg-info/PKG-INFO
pulumi_stripe.egg-info/SOURCES.txt
pulumi_stripe.egg-info/dependency_links.txt
pulumi_stripe.egg-info/not-zip-safe
pulumi_stripe.egg-info/requires.txt
pulumi_stripe.egg-info/top_level.txt
pulumi_stripe/config/__init__.py
pulumi_stripe/config/vars.py