Metadata-Version: 2.1
Name: pulumi-stripe
Version: 0.0.22
Summary: A Pulumi package for creating and managing Stripe resources.
Home-page: https://www.pulumi.com
License: Apache-2.0
Project-URL: Repository, https://github.com/georgegebbett/pulumi-stripe
Keywords: pulumi stripe category/cloud
Platform: UNKNOWN
Requires-Python: >=3.7
